sanmiao/__init__.py
sanmiao/bulk_processing.py
sanmiao/config.py
sanmiao/converters.py
sanmiao/loaders.py
sanmiao/reporting.py
sanmiao/sanmiao.py
sanmiao/solving.py
sanmiao/tagging.py
sanmiao/utils.py
sanmiao/xml_processing.py
sanmiao/xml_utils.py
sanmiao/data/dynasty_table_dump.csv
sanmiao/data/dynasty_tags.csv
sanmiao/data/era_table.csv
sanmiao/data/lunar_table_dump.csv
sanmiao/data/rul_can_name.csv
sanmiao/data/ruler_table.csv
sanmiao/data/ruler_tags.csv
sanmiao-0.2.3.dist-info/licenses/LICENSE
sanmiao-0.2.3.dist-info/METADATA
sanmiao-0.2.3.dist-info/WHEEL
sanmiao-0.2.3.dist-info/top_level.txt
sanmiao-0.2.3.dist-info/RECORD
