Metadata-Version: 2.4
Name: sanmiao
Version: 0.2.3
Summary: A Python package for date conversion to and from Chinese and Japanese historical calendars
Author-email: Daniel Patrick Morgan <daniel.morgan@college-de-france.fr>
Project-URL: Homepage, https://github.com/PotatoSinology/sanmiao
Project-URL: Repository, https://github.com/PotatoSinology/sanmiao.git
Project-URL: Issues, https://github.com/PotatoSinology/sanmiao/issues
Keywords: date conversion,Chinese calendar,Japanese calendar,history,history of astronomy,astronomy
Classifier: Development Status :: 3 - Alpha
Classifier: Intended Audience :: Education
Classifier: License :: OSI Approved :: MIT License
Classifier: Programming Language :: Python :: 3
Classifier: Programming Language :: Python :: 3.7
Classifier: Programming Language :: Python :: 3.8
Classifier: Programming Language :: Python :: 3.9
Classifier: Programming Language :: Python :: 3.10
Classifier: Programming Language :: Python :: 3.11
Classifier: Programming Language :: Python :: 3.12
Classifier: Programming Language :: Python :: 3.13
Classifier: Topic :: Scientific/Engineering
Requires-Python: >=3.7
License-File: LICENSE
Requires-Dist: pandas>=1.3.5
Requires-Dist: numpy>=1.21.0
Requires-Dist: lxml>=4.6.0
Requires-Dist: importlib_resources>=5.0; python_version < "3.9"
Dynamic: license-file
